LICENCE
README.md
test.py
redlog/__init__.py
redlog/__main__.py
redlog.egg-info/PKG-INFO
redlog.egg-info/SOURCES.txt
redlog.egg-info/dependency_links.txt
redlog.egg-info/requires.txt
redlog.egg-info/top_level.txt
redlog-1.4.dist-info/LICENCE
redlog-1.4.dist-info/METADATA
redlog-1.4.dist-info/WHEEL
redlog-1.4.dist-info/top_level.txt
redlog-1.4.dist-info/RECORD
