Metadata-Version: 2.1
Name: redlog
Version: 1.4
Summary: Python logger to Redis database with threading support
Home-page: https://github.com/lnstadrum/redlog
Author: lnstadrum
Author-email: 
License: UNKNOWN
Platform: UNKNOWN
License-File: LICENCE
Requires-Dist: redis
Requires-Dist: termcolor
